{"phon": "phon", "socio": "socio", "anth": "antho", "mechan": "mechan", "pneumo": "pneum", "son": "sono", "lexico": "lexic", "lique": "liqu", "gramo": "gram", "purge": "purge", "wit": "wit", "ography": "graph", "sacro": "sacro", "cylindr": "cylinder", "immuno": "immun", "rradi": "radio", "physio": "phys", "pept": "pepsia", "ggrand": "grand", "wonder": "wonder", "chroma": "chrome", "pater": "pater", "disput": "dispute", "grat": "grat", "sulph": "sulph", "make": "make", "jur": "jur", "stern": "sterno", "methyl": "methyl", "memor": "memor", "pneum": "pneum", "mmensur": "mensur", "eur": "euro", "sagaci": "sagac", "ostat": "stat", "judice": "judic", "five": "five", "stitue": "stitute", "phyl": "phylle", "divid": "divide", "visc": "visco", "cab": "cab", "cephale": "cephalo", "dominic": "dominic", "dendra": "dendro", "neuter": "neuter", "ffric": "frict", "mote": "mot", "patr": "pater", "write": "write", "ppress": "press", "ceros": "ceros", "oceano": "ocean", "decim": "decim", "monster": "monster", "ophthalmo": "ophthalmo", "graphi": "graph", "hagia": "hagio", "antho": "antho", "simil": "simil", "thanat": "thanat", "hetero": "hetero", "coel": "coelo", "ocrat": "crat", "citri": "citr", "anglo": "anglo", "palate": "palat", "lumin": "lumin", "corpuscle": "corpuscle", "rrupt": "rupt", "ssimul": "simul", "ply": "ply", "miracul": "miracle", "mane": "mania", "mechano": "mechan", "porno": "porn", "vesico": "vesico", "leps": "lept", "prehens": "prehens", "proxim": "proxim", "fit": "fit", "cycle": "cycle", "leuc": "leuk", "sati": "satis", "herpes": "herpes", "benefice": "benefice", "allege": "allege", "ograph": "graph", "cephal": "cephalo", "bak": "bake", "pict": "picto", "rumor": "rumor", "aero": "aero", "spir": "spir", "laryng": "laryng", "andr": "andro", "neutro": "neutr", "mys": "mys", "glamor": "glamour", "archi": "arch", "nucl": "nucleo", "cosmo": "cosmo", "saliva": "saliva", "kineto": "kinesio", "islamo": "islam", "valor": "valor", "ogram": "gram", "imperi": "empire", "pithecus": "pithec", "anthrop": "anthropo", "llumine": "lumin", "marc": "mark", "parlor": "parlor", "fabul": "fable", "czech": "czech", "histori": "history", "rhizo": "rhizo", "ventro": "ventr", "glycy": "gluc", "colour": "color", "marshal": "marshall", "value": "value", "counsel": "counsel", "clothes": "cloth", "sporo": "spor", "automata": "automata", "genea": "gen", "xyl": "xylo", "writ": "write", "humour": "humor", "solve": "solve", "schizo": "schizo", "cranio": "cranio", "ardour": "ardor", "escap": "escape", "phrene": "phrene", "mobil": "mobile", "tox": "toxico", "nucleo": "nucleo", "gyn": "gyn", "citr": "citr", "solute": "solut", "tubulo": "tubul", "mmigr": "migr", "spatio": "space", "particul": "particle", "fibro": "fiber", "septem": "septem", "ffront": "front", "pachyo": "pachy", "lipido": "lipo", "stoma": "stom", "ethn": "ethn", "enthus": "enthuse", "sauro": "saur", "saur": "saur", "petr": "petro", "tabul": "table", "maintain": "maintain", "proct": "proct", "angl": "anglo", "fflor": "flor", "correct": "correct", "prude": "prud", "acantho": "acantho", "glot": "glott", "strepto": "strepto", "lact": "lact", "prud": "prud", "ashe": "ash", "breathe": "breath", "tom": "tom", "nnul": "null", "crimino": "crimin", "olog": "log", "nihil": "nihil", "strat": "strat", "sym": "syn", "vertebr": "vertebr", "ogene": "gen", "physi": "phys", "judici": "judic", "ver": "veri", "thalamo": "thalam", "sperma": "sperm", "magn": "magn", "thir": "three", "three": "three", "extra": "extra", "rigour": "rigor", "holi": "holy", "gluc": "gluc", "mmerse": "merse", "lloc": "loc", "medico": "medic", "hypno": "hypn", "lubrici": "lubric", "dict": "dict", "cyon": "cyono", "cyono": "cyono", "amphibio": "amphibio", "astero": "astro", "cognise": "cognize", "tardi": "tard", "phot": "photo", "merse": "merse", "contr": "contra", "magnesio": "magnesio", "splendor": "splendor", "carri": "carry", "reside": "reside", "slumbr": "slumber", "equi": "equi", "clothe": "cloth", "archa": "archaeo", "plagi": "plagi", "morpho": "morph", "liqu": "liqu", "constabul": "constable", "chromo": "chrome", "toxi": "toxico", "null": "null", "hypn": "hypn", "veloci": "veloc", "rode": "rode", "set": "set", "logue": "log", "metall": "metal", "strept": "strepto", "numb": "numb", "kinesi": "kinesio", "inane": "inane", "history": "history", "brut": "brute", "alt": "alti", "quisit": "quire", "xanth": "xanth", "nocto": "noct", "fif": "five", "ferr": "ferr", "abdomen": "abdomen", "klept": "klepto", "ometr": "meter", "ffract": "fract", "cremate": "cremate", "scrupul": "scruple", "grub": "grub", "local": "local", "gaster": "gastr", "cephalo": "cephalo", "breed": "breed", "omane": "mania", "cclimate": "climate", "pseudo": "pseudo", "auricle": "auricle", "preside": "preside", "sider": "sider", "eventu": "event", "hum": "hume", "archaeo": "archaeo", "path": "patho", "legg": "leg", "phallo": "phallo", "oscill": "oscill", "puls": "pulse", "compet": "compete", "coiff": "coif", "phreno": "phrene", "testicle": "testicle", "pachy": "pachy", "miracle": "miracle", "vulv": "vulv", "robb": "rob", "squibb": "squib", "abund": "abound", "pteryg": "pterygo", "ocracie": "cracy", "vapour": "vapor", "spill": "spill", "ographo": "graph", "testicul": "testicle", "matur": "mature", "kerato": "kerat", "viscer": "viscer", "feroci": "feroc", "plagio": "plagi", "thermos": "thermo", "ccurs": "curse", "serve": "serve", "simpl": "simple", "psyche": "psycho", "offic": "office", "styl": "style", "fame": "fame", "megalo": "megalo", "sex": "sex", "phrenico": "phrene", "verse": "verse", "paed": "pedo", "savor": "savor", "thromb": "thrombo", "candid": "candid", "toluene": "toluene", "dexter": "dexter", "resid": "reside", "phobe": "phobe", "aquar": "aqua", "eros": "eros", "lucre": "lucre", "pithec": "pithec", "intra": "intra", "hemo": "hema", "sacr": "sacro", "solo": "solo", "win": "win", "lymph": "lymph", "glob": "globe", "chlor": "chlor", "imony": "mony", "omania": "mania", "holy": "holy", "synchr": "synchro", "ichthyo": "ichthy", "magico": "magic", "jigg": "jig", "hepat": "hepat", "val": "val", "recto": "rect", "cantho": "cantho", "genit": "genit", "glotto": "glott", "gnos": "gnose", "logic": "logic", "techno": "tech", "carrie": "carry", "veri": "veri", "catastroph": "catastrophe", "radi": "radio", "muscle": "muscle", "genito": "genit", "solut": "solut", "matri": "mater", "prob": "prob", "volcano": "volcan", "patho": "patho", "vertex": "vertex", "glott": "glott", "chondr": "chondr", "politic": "politic", "geront": "geront", "titan": "titan", "pleas": "please", "spectre": "spectr", "britain": "britain", "precoc": "precoc", "phys": "phys", "cyano": "cyano", "globe": "globe", "ccustom": "custom", "nome": "nomin", "radio": "radio", "frict": "frict", "jure": "jur", "pod": "podo", "jet": "jet", "bibli": "biblio", "automat": "automata", "oct": "octo", "fable": "fable", "rubr": "rubr", "ssembl": "semble", "maisonn": "maison", "ferro": "ferr", "lobo": "lobe", "pterus": "ptero", "navy": "navy", "glyc": "gluc", "navig": "navy", "starr": "star", "pedi": "podo", "knot": "knot", "occupy": "occupy", "climat": "climate", "lubric": "lubric", "dont": "donto", "lign": "line", "icon": "icon", "schol": "school", "spectr": "spectr", "nnot": "note", "politico": "politic", "nyx": "nyx", "ccultur": "culture", "curse": "curse", "flori": "flor", "cycl": "cycle", "aqua": "aqua", "gymno": "gymn", "klepto": "klepto", "ogramo": "gram", "hume": "hume", "ash": "ash", "cognize": "cognize", "judic": "judic", "valour": "valor", "loc": "loc", "pag": "page", "gregari": "greg", "flor": "flor", "stimul": "stimul", "xer": "xero", "oscope": "scope", "simul": "simul", "magneto": "magnet", "labio": "labio", "monstr": "monster", "fuse": "fuse", "wait": "wait", "volum": "volume", "script": "script", "mater": "mater", "long": "long", "indo": "indo", "clar": "clear", "amphibi": "amphibio", "gen": "gen", "cephaleo": "cephalo", "canvass": "canvas", "portrait": "portray", "supplic": "supplic", "vigor": "vigor", "visco": "visco", "brachy": "brachio", "mmetr": "meter", "succour": "succor", "rhin": "rhino", "brachi": "brachio", "brevi": "brevi", "gene": "gen", "phob": "phobe", "astro": "astro", "stomato": "stom", "cognis": "cognize", "clivitie": "clivity", "mom": "mom", "crime": "crimin", "viva": "vive", "grubb": "grub", "mobile": "mobile", "neur": "neuro", "lustre": "luster", "lympho": "lymph", "spati": "space", "humor": "humor", "endeavour": "endeavor", "metal": "metal", "winn": "win", "ogon": "gon", "pprehend": "prehens", "taut": "tauto", "noct": "noct", "benefic": "benefice", "exempl": "example", "cortico": "cortico", "amble": "amble", "presid": "preside", "megal": "megalo", "climate": "climate", "viscero": "viscer", "nnihil": "nihil", "vers": "verse", "pharmaco": "pharma", "elect": "electr", "sett": "set", "cann": "can", "pli": "ply", "vid": "vide", "antiqu": "antique", "spectro": "spectr", "lett": "let", "velox": "veloc", "glamour": "glamour", "matr": "mater", "clamour": "clamor", "pseud": "pseudo", "herpeto": "herpes", "title": "title", "quisite": "quire", "mmemor": "memor", "pollin": "pollen", "span": "spain", "ocracy": "cracy", "dactyle": "dactyl", "chrome": "chrome", "sperm": "sperm", "suct": "suck", "intro": "intra", "myso": "mys", "labia": "labio", "cortic": "cortico", "vehicle": "vehicle", "cracy": "cracy", "bronto": "bronto", "ferri": "ferr", "clear": "clear", "analogue": "analog", "lympha": "lymph", "cheiruso": "cheiruso", "mmers": "merse", "contra": "contra", "front": "front", "jett": "jet", "cremat": "cremate", "ology": "log", "arbitr": "arbiter", "dors": "dors", "hyster": "hyster", "tumour": "tumor", "ssimil": "simil", "equ": "equi", "ardor": "ardor", "ocul": "ocul", "lingu": "lingu", "vacue": "vacu", "stitute": "stitute", "stable": "stable", "momm": "mom", "calor": "calor", "sumpt": "sume", "rupt": "rupt", "giganto": "gigant", "tiger": "tiger", "gnose": "gnose", "abound": "abound", "thaumato": "thaumato", "parieto": "pariet", "tigr": "tiger", "artific": "artifice", "line": "line", "phall": "phallo", "tyran": "tyran", "example": "example", "vagino": "vagina", "disco": "disk", "loqu": "loqu", "spil": "spill", "raptor": "raptor", "can": "can", "latin": "latin", "register": "register", "simplex": "simple", "stan": "stan", "dorsi": "dors", "leuk": "leuk", "telluri": "tellur", "empire": "empire", "vac": "vacu", "centri": "center", "oligo": "olig", "armor": "armor", "glomer": "glomer", "volume": "volume", "thrombo": "thrombo", "mediocre": "mediocre", "seismo": "seism", "launder": "launder", "cracie": "cracy", "lob": "lobe", "ppreci": "preci", "solv": "solve", "bbrevi": "brevi", "iform": "form", "crani": "cranio", "oracle": "oracle", "centr": "center", "onym": "nym", "lobe": "lobe", "ggreg": "greg", "xeno": "xeno", "vapor": "vapor", "prime": "prim", "chem": "chem", "lept": "lept", "zygos": "zygo", "suffice": "suffice", "piano": "piano", "recuse": "recuse", "vibro": "vibr", "migr": "migr", "registr": "register", "nature": "nature", "andro": "andro", "quire": "quire", "formo": "form", "let": "let", "ambul": "amble", "ssect": "sect", "somni": "somn", "ffect": "fect", "nomino": "nomin", "pit": "pit", "physic": "phys", "vide": "vide", "toxico": "toxico", "hindr": "hinder", "auricul": "auricle", "tyrann": "tyran", "theo": "theo", "theatr": "theater", "rrhoea": "rrhoea", "nucle": "nucleo", "medal": "medal", "latino": "latin", "wintr": "winter", "cruc": "crux", "substance": "substance", "ffrict": "frict", "nausea": "nausea", "ventri": "ventr", "plen": "plen", "lev": "lev", "plement": "plement", "ventr": "ventr", "ffirm": "firm", "fluor": "fluor", "oculo": "ocul", "brute": "brute", "ssocio": "socio", "auto": "auto", "rob": "rob", "fugue": "fugue", "arbiter": "arbiter", "podo": "podo", "circle": "circle", "abdomin": "abdomen", "vive": "vive", "labor": "labor", "honor": "honor", "photo": "photo", "sy": "syn", "stega": "stego", "lucr": "lucre", "vale": "val", "sort": "sort", "eschat": "eschato", "chondro": "chondr", "fric": "frict", "soci": "socio", "lland": "land", "echin": "echino", "octa": "octo", "homo": "homo", "neuro": "neuro", "geo": "geo", "pugnaci": "pugnac", "platon": "plato", "stabile": "stable", "candor": "candor", "pathos": "patho", "cclimat": "climate", "spore": "spor", "phreni": "phrene", "nitr": "nitro", "land": "land", "fluoro": "fluor", "spele": "speleo", "phono": "phon", "bake": "bake", "octo": "octo", "curs": "curse", "somn": "somn", "press": "press", "pend": "pend", "ancestr": "ancestor", "theatre": "theater", "crux": "crux", "extro": "extra", "mendac": "mendac", "titano": "titan", "viv": "vive", "vag": "vague", "meteoro": "meteo", "cyno": "cyno", "honour": "honor", "tachy": "tachyo", "stimulus": "stimul", "thaumat": "thaumato", "mania": "mania", "jewel": "jewel", "stitu": "stitute", "obsequy": "obsequi", "cauda": "cauda", "mainten": "maintain", "ccurse": "curse", "muscul": "muscle", "fibr": "fiber", "table": "table", "witt": "wit", "laundr": "launder", "singl": "single", "fect": "fect", "neglig": "neglig", "vacu": "vacu", "rrhea": "rrhoea", "ichthy": "ichthy", "otype": "typo", "techn": "tech", "anthropo": "anthropo", "crimin": "crimin", "sect": "sect", "liber": "liber", "culture": "culture", "hydr": "hydr", "singul": "single", "sagac": "sagac", "china": "china", "cumul": "cumul", "ocean": "ocean", "biblio": "biblio", "phago": "phage", "odour": "odor", "mict": "mict", "gyno": "gyn", "reticul": "reticule", "duc": "duct", "leg": "leg", "gram": "gram", "nom": "nomin", "gluco": "gluc", "flavor": "flavor", "stylo": "style", "igraph": "graph", "labour": "labor", "ssemble": "semble", "picto": "picto", "mensur": "mensur", "hali": "halio", "marshall": "marshall", "grate": "grat", "form": "form", "beast": "beast", "canvas": "canvas", "longi": "long", "fogg": "fog", "india": "indo", "patro": "pater", "rationale": "rational", "tauto": "tauto", "mature": "mature", "physico": "phys", "techni": "tech", "clivity": "clivity", "ann": "ann", "corrig": "correct", "pub": "pube", "vigour": "vigor", "candide": "candid", "ministr": "minister", "distil": "distill", "pteryx": "pteryxo", "nigr": "negro", "dactyl": "dactyl", "locut": "loqu", "chemo": "chem", "alti": "alti", "xylo": "xylo", "veloc": "veloc", "tube": "tube", "single": "single", "office": "office", "pariet": "pariet", "kinet": "kinesio", "chrom": "chrome", "anthrope": "anthropo", "compan": "compan", "sphen": "spheno", "specter": "spectr", "pharyngo": "pharyng", "lopho": "lopho", "cardi": "cardio", "britann": "britain", "llumin": "lumin", "scope": "scope", "grand": "grand", "pleni": "plen", "sens": "sense", "lexic": "lexic", "psycho": "psycho", "knott": "knot", "aqui": "aqua", "hier": "hiero", "methylo": "methyl", "hydro": "hydr", "discourse": "discours", "pedagog": "pedagogue", "bath": "bath", "school": "school", "rhino": "rhino", "sense": "sense", "melano": "melano", "medic": "medic", "suck": "suck", "magnet": "magnet", "mot": "mot", "inan": "inane", "contro": "contra", "breath": "breath", "hour": "hour", "analog": "analog", "stabil": "stable", "dorso": "dors", "recti": "rect", "trapp": "trap", "dactylo": "dactyl", "phospho": "phosphor", "dicta": "dict", "lex": "lexic", "petro": "petro", "panto": "panto", "pyr": "pyro", "type": "typo", "strato": "strat", "cyan": "cyano", "war": "war", "axe": "axe", "pneumono": "pneum", "melan": "melano", "necro": "necro", "grandi": "grand", "filter": "filter", "urge": "urge", "initi": "initi", "gigant": "gigant", "catastrophe": "catastrophe", "ptero": "ptero", "ssoci": "socio", "vulvo": "vulv", "soli": "solo", "ample": "ample", "fiber": "fiber", "pterid": "ptero", "icure": "cure", "clamor": "clamor", "nyxo": "nyx", "steth": "stetho", "cide": "icide", "echino": "echino", "carpentr": "carpenter", "synchro": "synchro", "tempor": "tempor", "num": "numb", "thanato": "thanat", "suffic": "suffice", "micro": "micro", "phren": "phrene", "endeavor": "endeavor", "amphibo": "amphibio", "substant": "substance", "automaton": "automata", "ruber": "rubr", "simple": "simple", "nomin": "nomin", "distatr": "disaster", "nnull": "null", "chrono": "chrono", "toxo": "toxico", "thylaco": "thylaco", "domin": "domin", "bred": "breed", "thalass": "thalasso", "critic": "critic", "bragg": "brag", "icab": "cab", "precoci": "precoc", "patern": "pater", "the": "theo", "fugit": "fugue", "amphib": "amphibio", "vagin": "vagina", "morph": "morph", "child": "child", "transit": "transit", "peda": "pedo", "ped": "podo", "tech": "tech", "manu": "mani", "rumour": "rumor", "sono": "sono", "best": "beast", "niger": "negro", "tub": "tube", "islam": "islam", "tachyo": "tachyo", "dispute": "dispute", "sume": "sume", "custom": "custom", "phil": "philo", "antique": "antique", "pharma": "pharma", "squib": "squib", "ppos": "pose", "sanct": "sanct", "compete": "compete", "tography": "graph", "enthuse": "enthuse", "clam": "clam", "sexu": "sex", "dendr": "dendro", "abstin": "abstin", "palat": "palat", "lespy": "lepsy", "prehend": "prehens", "astr": "astro", "rancor": "rancor", "cetus": "cetuso", "rational": "rational", "reticule": "reticule", "gynaec": "gynaec", "aer": "aero", "hide": "hide", "compar": "compare", "xero": "xero", "brachio": "brachio", "fratr": "fratern", "phone": "phon", "grapho": "graph", "administr": "administer", "chin": "china", "hagi": "hagio", "pitt": "pit", "parlour": "parlor", "speleo": "speleo", "thalam": "thalam", "fam": "fame", "disc": "disk", "homoeo": "homeo", "spor": "spor", "geronto": "geront", "daguerre": "daguerreo", "apoplex": "apoplex", "tubul": "tubul", "bronch": "bronchi", "micto": "mict", "chemi": "chem", "clamm": "clam", "erot": "eros", "vulva": "vulv", "fruct": "fruit", "discurs": "discours", "ccumul": "cumul", "concil": "concile", "remember": "remember", "contain": "contain", "stetho": "stetho", "libert": "liber", "syn": "syn", "sulf": "sulph", "bathe": "bath", "seism": "seism", "pube": "pube", "germin": "germ", "luster": "luster", "dermo": "derm", "preci": "preci", "titul": "title", "kinesio": "kinesio", "hid": "hide", "init": "initi", "ccompan": "compan", "mers": "merse", "hor": "hour", "cure": "cure", "logo": "log", "cardio": "cardio", "elig": "electr", "mediocr": "mediocre", "wedge": "wedge", "myth": "myth", "children": "child", "zyg": "zygo", "schiz": "schizo", "donto": "donto", "franco": "franco", "corpuscul": "corpuscle", "lacto": "lact", "ssure": "sure", "nycto": "noct", "gloss": "gloss", "pollen": "pollen", "czecho": "czech", "sancti": "sanct", "carry": "carry", "homeo": "homeo", "procto": "proct", "gastro": "gastr", "brit": "britain", "cylinder": "cylinder", "satis": "satis", "magic": "magic", "ancestor": "ancestor", "follicul": "follicle", "sexo": "sex", "color": "color", "aster": "astro", "remembr": "remember", "pedo": "pedo", "gnath": "gnath", "vesic": "vesico", "slumber": "slumber", "hepato": "hepat", "vertices": "vertex", "mendaci": "mendac", "agri": "agri", "mmingle": "mingle", "scribe": "script", "cumbr": "cumber", "phosphor": "phosphor", "histor": "history", "jig": "jig", "pharyng": "pharyng", "lingua": "lingu", "tellur": "tellur", "spermato": "sperm", "cetuso": "cetuso", "cyclo": "cycle", "administer": "administer", "pteryxo": "pteryxo", "gymn": "gymn", "lacti": "lact", "bronchi": "bronchi", "ethno": "ethn", "page": "page", "occup": "occupy", "fface": "face", "apoplect": "apoplex", "rhiza": "rhizo", "pulse": "pulse", "rrode": "rode", "aut": "auto", "llevi": "lev", "pprehens": "prehens", "aque": "aqua", "pedagogue": "pedagogue", "ssolve": "solve", "integr": "integer", "ggrieve": "grieve", "sure": "sure", "graph": "graph", "vehicul": "vehicle", "cosm": "cosmo", "onto": "onto", "semble": "semble", "phage": "phage", "spire": "spir", "pede": "podo", "winter": "winter", "enter": "enter", "glosso": "gloss", "contin": "contain", "vibr": "vibr", "leuko": "leuk", "space": "space", "matern": "mater", "star": "star", "pprob": "prob", "bio": "bio", "lepto": "lept", "locate": "locate", "splendour": "splendor", "pubo": "pube", "rect": "rect", "ometer": "meter", "phyll": "phylle", "palato": "palat", "pterygo": "pterygo", "kerat": "kerat", "harmony": "harmon", "sancto": "sanct", "scop": "scope", "negro": "negro", "mani": "mani", "ologo": "log", "transi": "transit", "style": "style", "writt": "write", "probe": "prob", "coif": "coif", "spitt": "spit", "tyranno": "tyran", "harmon": "harmon", "vivi": "vive", "gynec": "gynaec", "latina": "latin", "armour": "armor", "critique": "critic", "metallo": "metal", "juris": "jur", "phosphoro": "phosphor", "ppend": "pend", "goat": "goat", "meteor": "meteo", "made": "make", "medall": "medal", "derma": "derm", "immun": "immun", "otom": "tom", "ceps": "ceps", "cogniz": "cognize", "hinder": "hinder", "phylle": "phylle", "succor": "succor", "phag": "phage", "ceras": "ceraso", "cyn": "cyno", "dermato": "derm", "ax": "axe", "gastr": "gastr", "ogr": "ogr", "typo": "typo", "drome": "drome", "nomen": "nomin", "lepti": "lept", "leuco": "leuk", "particle": "particle", "serv": "serve", "laryngo": "laryng", "cloth": "cloth", "carpenter": "carpenter", "distill": "distill", "urg": "urge", "suppli": "supplic", "odor": "odor", "otoluene": "toluene", "mony": "mony", "lipo": "lipo", "micr": "micro", "fratern": "fratern", "enn": "ann", "harbour": "harbor", "ogre": "ogr", "portray": "portray", "metr": "meter", "daguerreo": "daguerreo", "nephro": "nephro", "prot": "proto", "flavour": "flavor", "labi": "labio", "candour": "candor", "phile": "philo", "please": "please", "hagio": "hagio", "savour": "savor", "patri": "pater", "icide": "icide", "escape": "escape", "fog": "fog", "duct": "duct", "circul": "circle", "lingui": "lingu", "thalasso": "thalasso", "euro": "euro", "istan": "stan", "saura": "saur", "trap": "trap", "thylac": "thylaco", "eschato": "eschato", "ffuse": "fuse", "calori": "calor", "logico": "logic", "leptic": "lepsy", "nul": "null", "pian": "piano", "ppose": "pose", "necr": "necro", "somno": "somn", "arch": "arch", "blew": "blow", "drom": "drome", "therm": "thermo", "phyllo": "phylle", "locale": "local", "citro": "citr", "temporo": "tempor", "feroc": "feroc", "plato": "plato", "grieve": "grieve", "audio": "audio", "cheirus": "cheiruso", "brachion": "brachio", "firm": "firm", "dendro": "dendro", "vagina": "vagina", "tecn": "tech", "pyro": "pyro", "fract": "fract", "meter": "meter", "rancour": "rancor", "halio": "halio", "rigor": "rigor", "chron": "chrono", "germ": "germ", "otypo": "typo", "xanthos": "xanth", "ceraso": "ceraso", "pneumat": "pneum", "glutin": "glutin", "absten": "abstin", "event": "event", "regi": "regi", "gglutin": "glutin", "sidero": "sider", "vague": "vague", "prim": "prim", "olig": "olig", "oscop": "scope", "saurus": "saur", "fruit": "fruit", "face": "face", "warr": "war", "brag": "brag", "pugnac": "pugnac", "decem": "decim", "pictus": "picto", "gglomer": "glomer", "wedg": "wedge", "stat": "stat", "crat": "crat", "icono": "icon", "longo": "long", "valua": "value", "zygo": "zygo", "imper": "empire", "waite": "wait", "divis": "divide", "ophthalm": "ophthalmo", "goats": "goat", "vertebro": "vertebr", "cerat": "cerato", "angul": "angle", "stom": "stom", "herpet": "herpes", "brachyo": "brachio", "phosph": "phosphor", "nycho": "nycho", "ssort": "sort", "saliv": "saliva", "caud": "cauda", "constable": "constable", "obsequi": "obsequi", "juri": "jur", "obey": "obey", "harbor": "harbor", "chloro": "chlor", "reg": "regi", "xen": "xeno", "uter": "utero", "negr": "negro", "sacri": "sacro", "rex": "regi", "pneumon": "pneum", "entr": "enter", "nitro": "nitro", "hiero": "hiero", "aud": "audio", "ogen": "gen", "sacra": "sacro", "follicle": "follicle", "derm": "derm", "silic": "silic", "acanth": "acantho", "canth": "cantho", "spain": "spain", "ppropri": "propri", "dermat": "derm", "indi": "indo", "cyber": "cyber", "alleg": "allege", "purg": "purge", "ttribute": "tribute", "note": "note", "pharmac": "pharma", "lustr": "luster", "proto": "proto", "oracul": "oracle", "theater": "theater", "tribute": "tribute", "lumine": "lumin", "pplement": "plement", "angle": "angle", "dextr": "dexter", "pose": "pose", "minister": "minister", "ampl": "ample", "utero": "utero", "tard": "tard", "negl": "neglig", "propri": "propri", "jewell": "jewel", "volcan": "volcan", "silico": "silic", "nym": "nym", "porn": "porn", "primo": "prim", "xantho": "xanth", "divide": "divide", "canad": "canada", "medi": "medic", "mingle": "mingle", "obei": "obey", "hystero": "hyster", "disaster": "disaster", "agro": "agri", "llocate": "locate", "scruple": "scruple", "cerato": "cerato", "mytho": "myth", "canada": "canada", "oscillo": "oscill", "gon": "gon", "pter": "ptero", "fitt": "fit", "blow": "blow", "mark": "mark", "thermo": "thermo", "nause": "nausea", "chondri": "chondr", "gnatho": "gnath", "dominica": "dominic", "duce": "duct", "sembl": "semble", "pepsia": "pepsia", "meteo": "meteo", "log": "log", "archeo": "archaeo", "stego": "stego", "artifice": "artifice", "maison": "maison", "wondr": "wonder", "sterno": "sterno", "center": "center", "lymphi": "lymph", "greg": "greg", "filtr": "filter", "council": "counsel", "philo": "philo", "pprobe": "prob", "stome": "stom", "nephr": "nephro", "natur": "nature", "tyrant": "tyran", "hema": "hema", "spheno": "spheno", "coelo": "coelo", "glyco": "gluc", "loco": "loc", "disk": "disk", "integer": "integer", "tumor": "tumor", "concile": "concile", "neutr": "neutr", "cumber": "cumber", "recus": "recuse", "pproxim": "proxim", "psych": "psycho", "valu": "value", "nyct": "noct"}